jm_llm_agent/__init__.py
jm_llm_agent/llm/__init__.py
jm_llm_agent/llm/base.py
jm_llm_agent/llm/claude.py
jm_llm_agent/llm/function.py
jm_llm_agent/llm/gemini.py
jm_llm_agent/llm/gpt.py
jm_llm_agent/llm/llm.py
jm_llm_agent/tools/__init__.py
jm_llm_agent/tools/google.py
jm_llm_agent/tools/seekingalpha.py
jm_llm_agent/tools/stock_data.py
jm_llm_agent/tools/tel_notify.py
jm_llm_agent/tools/web.py
jm_llm_agent/utils/str_util.py
jm_llm_agent-0.1.202501060525.dist-info/METADATA
jm_llm_agent-0.1.202501060525.dist-info/WHEEL
jm_llm_agent-0.1.202501060525.dist-info/RECORD
